TextBooster/Text_Generation.py
TextBooster/__init__.py
TextBooster-0.3.dist-info/LICENSE.txt
TextBooster-0.3.dist-info/METADATA
TextBooster-0.3.dist-info/WHEEL
TextBooster-0.3.dist-info/top_level.txt
TextBooster-0.3.dist-info/RECORD
